odoo/addons/sale_disable_consolidated_billing/README.rst
odoo/addons/sale_disable_consolidated_billing/__init__.py
odoo/addons/sale_disable_consolidated_billing/__manifest__.py
odoo/addons/sale_disable_consolidated_billing/models/__init__.py
odoo/addons/sale_disable_consolidated_billing/models/sale_make_invoice_advance.py
odoo/addons/sale_disable_consolidated_billing/readme/CONTRIBUTORS.md
odoo/addons/sale_disable_consolidated_billing/readme/DESCRIPTION.md
odoo/addons/sale_disable_consolidated_billing/static/description/icon.png
odoo/addons/sale_disable_consolidated_billing/static/description/index.html
odoo/addons/sale_disable_consolidated_billing/tests/__init__.py
odoo/addons/sale_disable_consolidated_billing/tests/test_sale_automatic_workflow_order_type.py
odoo_addon_sale_disable_consolidated_billing-17.0.1.0.0.1.dist-info/METADATA
odoo_addon_sale_disable_consolidated_billing-17.0.1.0.0.1.dist-info/WHEEL
odoo_addon_sale_disable_consolidated_billing-17.0.1.0.0.1.dist-info/top_level.txt
odoo_addon_sale_disable_consolidated_billing-17.0.1.0.0.1.dist-info/RECORD
